lydwhitt_tools/KDE.py
lydwhitt_tools/__init__.py
lydwhitt_tools/filter.py
lydwhitt_tools/formula_recalc.py
lydwhitt_tools/mahalanobis.py
lydwhitt_tools-1.1.3.dist-info/licenses/LICENSE
lydwhitt_tools-1.1.3.dist-info/METADATA
lydwhitt_tools-1.1.3.dist-info/WHEEL
lydwhitt_tools-1.1.3.dist-info/top_level.txt
lydwhitt_tools-1.1.3.dist-info/RECORD
