Metadata-Version: 2.4
Name: lydwhitt-tools
Version: 1.1.3
Summary: Petrology tools
Author: Lydia Whittaker
License: MIT
Project-URL: Homepage, https://github.com/lydwhitt7/Lydwhitt_tools
Project-URL: Repository, https://github.com/lydwhitt7/Lydwhitt_tools
Project-URL: Issues, https://github.com/lydwhitt7/Lydwhitt_tools/issues
Classifier: Programming Language :: Python :: 3
Classifier: Programming Language :: Python :: 3 :: Only
Classifier: License :: OSI Approved :: MIT License
Classifier: Operating System :: OS Independent
Classifier: Intended Audience :: Science/Research
Classifier: Topic :: Scientific/Engineering
Requires-Python: >=3.8
License-File: LICENSE
Requires-Dist: numpy
Requires-Dist: pandas
Requires-Dist: scipy
Dynamic: license-file
